docetl/__init__.py
docetl/api.py
docetl/base_schemas.py
docetl/cli.py
docetl/config_wrapper.py
docetl/console.py
docetl/containers.py
docetl/dataset.py
docetl/optimizer.py
docetl/parsing_tools.py
docetl/ratelimiter.py
docetl/runner.py
docetl/schemas.py
docetl/utils.py
docetl/utils_dataset.py
docetl/utils_evaluation.py
docetl/apis/__init__.py
docetl/apis/pd_accessors.py
docetl/moar/MOARSearch.py
docetl/moar/Node.py
docetl/moar/ParetoFrontier.py
docetl/moar/__init__.py
docetl/moar/cli_helpers.py
docetl/moar/search_utils.py
docetl/operations/__init__.py
docetl/operations/add_uuid.py
docetl/operations/base.py
docetl/operations/cluster.py
docetl/operations/clustering_utils.py
docetl/operations/code_operations.py
docetl/operations/equijoin.py
docetl/operations/extract.py
docetl/operations/filter.py
docetl/operations/gather.py
docetl/operations/link_resolve.py
docetl/operations/map.py
docetl/operations/rank.py
docetl/operations/reduce.py
docetl/operations/resolve.py
docetl/operations/sample.py
docetl/operations/scan.py
docetl/operations/split.py
docetl/operations/topk.py
docetl/operations/unnest.py
docetl/operations/utils/__init__.py
docetl/operations/utils/api.py
docetl/operations/utils/cache.py
docetl/operations/utils/llm.py
docetl/operations/utils/progress.py
docetl/operations/utils/validation.py
docetl/optimizers/__init__.py
docetl/optimizers/join_optimizer.py
docetl/optimizers/reduce_optimizer.py
docetl/optimizers/utils.py
docetl/optimizers/map_optimizer/__init__.py
docetl/optimizers/map_optimizer/config_generators.py
docetl/optimizers/map_optimizer/evaluator.py
docetl/optimizers/map_optimizer/operation_creators.py
docetl/optimizers/map_optimizer/optimizer.py
docetl/optimizers/map_optimizer/plan_generators.py
docetl/optimizers/map_optimizer/prompt_generators.py
docetl/optimizers/map_optimizer/utils.py
docetl/reasoning_optimizer/AGENT.md
docetl/reasoning_optimizer/agent.py
docetl/reasoning_optimizer/instantiate_schemas.py
docetl/reasoning_optimizer/load_data.py
docetl-0.2.6.dist-info/METADATA
docetl-0.2.6.dist-info/WHEEL
docetl-0.2.6.dist-info/entry_points.txt
docetl-0.2.6.dist-info/licenses/LICENSE
docetl-0.2.6.dist-info/RECORD
