Metadata-Version: 2.4
Name: docetl
Version: 0.2.6
Summary: ETL with LLM operations.
Author-email: Shreya Shankar <shreyashankar@berkeley.edu>
License: MIT
License-File: LICENSE
Requires-Python: >=3.10
Requires-Dist: asteval>=1.0.4
Requires-Dist: boto3>=1.37.27
Requires-Dist: diskcache>=5.6.3
Requires-Dist: frozendict>=2.4.4
Requires-Dist: jsonschema>=4.23.0
Requires-Dist: litellm>=1.75.4
Requires-Dist: lzstring>=1.0.4
Requires-Dist: matplotlib>=3.7.0
Requires-Dist: modal>=0.64.0
Requires-Dist: nltk>=3.8.0
Requires-Dist: numpy>=1.24.0
Requires-Dist: pandas>=2.3.0
Requires-Dist: pydantic>=2.9.2
Requires-Dist: pyrate-limiter>=3.7.0
Requires-Dist: python-levenshtein>=0.21.0
Requires-Dist: python-multipart>=0.0.20
Requires-Dist: rank-bm25>=0.2.2
Requires-Dist: rapidfuzz>=3.10.0
Requires-Dist: rich>=13.7.1
Requires-Dist: scikit-learn>=1.5.2
Requires-Dist: scipy>=1.10.0
Requires-Dist: tqdm>=4.66.4
Requires-Dist: typer>=0.16.0
Requires-Dist: websockets>=13.1
Provides-Extra: parsing
Requires-Dist: azure-ai-documentintelligence>=1.0.0b4; extra == 'parsing'
Requires-Dist: openpyxl>=3.1.5; extra == 'parsing'
Requires-Dist: paddlepaddle<3.2,>=2.6.2; extra == 'parsing'
Requires-Dist: pydub>=0.25.1; extra == 'parsing'
Requires-Dist: pymupdf>=1.24.10; extra == 'parsing'
Requires-Dist: python-docx>=1.1.2; extra == 'parsing'
Requires-Dist: python-pptx>=1.0.2; extra == 'parsing'
Provides-Extra: retrieval
Requires-Dist: lancedb>=0.7.0; extra == 'retrieval'
Provides-Extra: server
Requires-Dist: azure-ai-documentintelligence>=1.0.0b4; extra == 'server'
Requires-Dist: azure-ai-formrecognizer>=3.3.3; extra == 'server'
Requires-Dist: docling>=2.5.2; extra == 'server'
Requires-Dist: fastapi>=0.115.4; extra == 'server'
Requires-Dist: httpx>=0.27.2; extra == 'server'
Requires-Dist: uvicorn>=0.31.0; extra == 'server'
